InstaToolKit/__init__.py
InstaToolKit/instagram.py
tests/__init__.py
tests/test_instagram.py
InstaToolkit-0.1.3.dist-info/METADATA
InstaToolkit-0.1.3.dist-info/WHEEL
InstaToolkit-0.1.3.dist-info/top_level.txt
InstaToolkit-0.1.3.dist-info/RECORD
