Metadata-Version: 2.1
Name: InstaToolkit
Version: 0.1.3
Summary: A versatile toolkit for automating Instagram interactions
Home-page: https://github.com/HimashaHerath/InstaToolkit
Author: Himasha Herath
Author-email: himasha626@gmail.com
Classifier: Development Status :: 3 - Alpha
Classifier: Intended Audience :: Developers
Classifier: Topic :: Software Development :: Build Tools
Classifier: License :: OSI Approved :: MIT License
Classifier: Programming Language :: Python :: 3
Classifier: Programming Language :: Python :: 3.6
Classifier: Programming Language :: Python :: 3.7
Classifier: Programming Language :: Python :: 3.8
Classifier: Programming Language :: Python :: 3.9
Classifier: Programming Language :: Python :: 3.10
Requires-Python: >=3.6
Requires-Dist: requests
